{
    "openapi": "3.0.0",
    "info": {
        "title": "Microserviço de Importação v1.0 - Documentação da API.",
        "description": "Challenge5 SOAT8 Grupo 03 - Microserviço de Importação e Processamento",
        "version": "1.0.0"
    },
    "servers": [
        {
            "url": "http://localhost:3000/"
        }
    ],
    "paths": {
        "/import": {
            "post": {
                "summary": "Inicia a importação de um vídeo",
                "description": "Recebe informações detalhadas do vídeo, usuário e configurações para iniciar o processo de importação via SNS.",
                "requestBody": {
                    "required": true,
                    "content": {
                        "application/json": {
                            "schema": {
                                "type": "object",
                                "properties": {
                                    "video": {
                                        "type": "object",
                                        "properties": {
                                            "id_video": { "type": "string", "example": "550e8400-e29b-41d4-a716-446655440000" },
                                            "title": { "type": "string", "example": "Título do vídeo" },
                                            "description": { "type": "string", "example": "Descrição do vídeo" },
                                            "filename": { "type": "string", "example": "video.mp4" },
                                            "file_size": { "type": "integer", "example": 104857600 },
                                            "full_path": { "type": "string", "example": "s3://caminho/para/o/video.mp4" },
                                            "duration": { "type": "integer", "example": 300 },
                                            "framerate": { "type": "integer", "example": 30 }
                                        },
                                        "required": ["id_video", "full_path"]
                                    },
                                    "user": {
                                        "type": "object",
                                        "properties": {
                                            "id_usuario": { "type": "string", "example": "123e4567-e89b-12d3-a456-426614174000" },
                                            "email": { "type": "string", "example": "usuario@exemplo.com" }
                                        },
                                        "required": ["id_usuario"]
                                    },
                                    "config": {
                                        "type": "object",
                                        "properties": {
                                            "output_format": { "type": "string", "example": "png" },
                                            "resolution": { "type": "string", "example": "1920x1080" },
                                            "interval": { "type": "integer", "example": 20 }
                                        },
                                        "required": ["output_format"]
                                    }
                                },
                                "required": ["video", "user", "config"],
                                "example": {
                                    "video": {
                                        "id_video": "550e8400-e29b-41d4-a716-446655440000",
                                        "title": "Título do vídeo",
                                        "description": "Descrição do vídeo",
                                        "filename": "video.mp4",
                                        "file_size": 104857600,
                                        "full_path": "s3://caminho/para/o/video.mp4",
                                        "duration": 300,
                                        "framerate": 30
                                    },
                                    "user": {
                                        "id_usuario": "123e4567-e89b-12d3-a456-426614174000",
                                        "email": "usuario@exemplo.com"
                                    },
                                    "config": {
                                        "output_format": "png",
                                        "resolution": "1920x1080",
                                        "interval": 20
                                    }
                                }
                            }
                        }
                    }
                },
                "responses": {
                    "200": {
                        "description": "Importação iniciada com sucesso",
                        "content": {
                            "application/json": {
                                "schema": {
                                    "type": "object",
                                    "properties": {
                                        "message": { "type": "string", "example": "Importação iniciada com sucesso" }
                                    }
                                }
                            }
                        }
                    },
                    "400": {
                        "description": "Campos obrigatórios faltando",
                        "content": {
                            "application/json": {
                                "schema": {
                                    "type": "object",
                                    "properties": {
                                        "error": { "type": "string", "example": "Campos obrigatórios faltando (id_video, full_path, id_usuario, output_format)" }
                                    }
                                }
                            }
                        }
                    },
                    "500": {
                        "description": "Erro interno no servidor",
                        "content": {
                            "application/json": {
                                "schema": {
                                    "type": "object",
                                    "properties": {
                                        "error": { "type": "string", "example": "Erro interno ao processar a importação" }
                                    }
                                }
                            }
                        }
                    }
                }
            }
        }
    },
    "components": {
        "securitySchemes": {
            "bearerAuth": {
                "type": "http",
                "scheme": "bearer"
            }
        }
    }
}
